resourcerer/__init__.py
resourcerer/delete_from_onedrive.py
resourcerer/get_from_onedrive.py
resourcerer/get_resources.py
resourcerer/parse_yaml.py
resourcerer/send_resources.py
resourcerer/send_to_onedrive.py
resourcerer/shared.py
test/__init__.py
test/onedrive/__init__.py
test/onedrive/test_download.py
test/onedrive/test_upload.py
resourcerer-1.0.0.dist-info/METADATA
resourcerer-1.0.0.dist-info/WHEEL
resourcerer-1.0.0.dist-info/entry_points.txt
resourcerer-1.0.0.dist-info/top_level.txt
resourcerer-1.0.0.dist-info/RECORD
