Metadata-Version: 2.1
Name: resourcerer
Version: 1.0.0
Summary: Gets resource files for testing from a configured remote location allowing you to separate code from test resources
Home-page: https://github.com/Technica-Engineering/resourcerer
Author: Krzysztof Czarnecki
Author-email: krzysztof.czarnecki@technica-engineering.de
License: MIT
Keywords: automation,testing,resources,download,onedrive
Platform: UNKNOWN
Classifier: License :: OSI Approved :: MIT License
Classifier: Programming Language :: Python :: 3
Classifier: Programming Language :: Python :: 3.7
Requires-Python: >=3.7
Requires-Dist: pyyaml
Provides-Extra: dev
Requires-Dist: flake8 ; extra == 'dev'
Requires-Dist: twine ; extra == 'dev'
Requires-Dist: setuptools ; extra == 'dev'
Requires-Dist: autopep8 ; extra == 'dev'
